gcstructuredlogger/__init__.py
gcstructuredlogger/structuredlogger.py
google_cloud_structured_logger-0.1.1.dist-info/LICENSE
google_cloud_structured_logger-0.1.1.dist-info/METADATA
google_cloud_structured_logger-0.1.1.dist-info/WHEEL
google_cloud_structured_logger-0.1.1.dist-info/top_level.txt
google_cloud_structured_logger-0.1.1.dist-info/RECORD
