Metadata-Version: 2.1
Name: google-cloud-structured-logger
Version: 0.1.1
Summary: A Python library adding a structured log formatter for Google Cloud
Home-page: https://github.com/noy72/google-cloud-structured-logger
Author: noy72
Author-email: noy72@protonmail.com
License: BSD
Platform: UNKNOWN
Classifier: Development Status :: 3 - Alpha
Classifier: Intended Audience :: Developers
Classifier: License :: OSI Approved :: BSD License
Classifier: Operating System :: OS Independent
Classifier: Programming Language :: Python :: 3
Classifier: Programming Language :: Python :: 3.6
Classifier: Programming Language :: Python :: 3.7
Classifier: Programming Language :: Python :: 3.8
Classifier: Programming Language :: Python :: 3.9
Classifier: Programming Language :: Python :: 3.10
Classifier: Topic :: System :: Logging
Requires-Python: >=3.5, <4
License-File: LICENSE
Requires-Dist: python-json-logger
